awsync/__init__.py
awsync/__main__.py
awsync/client.py
awsync/models/__init__.py
awsync/models/aws.py
awsync/models/http.py
awsync/models/strenum.py
awsync/py.typed
awsync/request.py
awsync-0.4.5.dist-info/LICENSE
awsync-0.4.5.dist-info/METADATA
awsync-0.4.5.dist-info/WHEEL
awsync-0.4.5.dist-info/RECORD
