Metadata-Version: 2.1
Name: awsync
Version: 0.4.5
Summary: An asynchronous, fully-typed AWS API library with a focus on being understandable, reliable, and maintainable.
Home-page: https://github.com/JKCT/awsync
License: Apache-2.0
Keywords: aws,async,boto,request,sdk,typed
Author: JKCT
Author-email: jkct@visceralfx.com
Requires-Python: >=3.8,<4.0
Classifier: Development Status :: 4 - Beta
Classifier: License :: OSI Approved :: Apache Software License
Classifier: Operating System :: OS Independent
Classifier: Programming Language :: Python :: 3
Classifier: Programming Language :: Python :: 3.8
Classifier: Programming Language :: Python :: 3.9
Classifier: Programming Language :: Python :: 3.10
Classifier: Programming Language :: Python :: 3.11
Classifier: Programming Language :: Python :: 3.12
Classifier: Typing :: Typed
Requires-Dist: httpx (>=0.27.0,<0.28.0)
Project-URL: Documentation, https://jkct.github.io/awsync/
Project-URL: Repository, https://github.com/JKCT/awsync
